plibby/__init__.py
plibby/log.py
plibby-0.1.0.dist-info/WHEEL
plibby-0.1.0.dist-info/METADATA
plibby-0.1.0.dist-info/RECORD
